dictclass.py
setup.cfg
setup.py
dictclass.egg-info/PKG-INFO
dictclass.egg-info/SOURCES.txt
dictclass.egg-info/dependency_links.txt
dictclass.egg-info/top_level.txt