Metadata-Version: 1.1
Name: dictclass
Version: 0.0.1
Summary: Write inheritable dicts using class syntax.
Home-page: https://github.com/dhilst/py-dictclass
Author: Daniel Hilst Selli
Author-email: danielhilst@gmail.com
License: Apache 2.0
Download-URL: https://github.com/dhilst/py-dictclass/archive/master.zip
Keywords: development
Platform: UNKNOWN
Classifier: Development Status :: 3 - Alpha
Classifier: Intended Audience :: Developers
Classifier: Topic :: Software Development :: Libraries
Classifier: License :: OSI Approved :: Apache Software License
Classifier: Programming Language :: Python :: 2
Classifier: Programming Language :: Python :: 3
